{
  "localizedName": "Land Manufacture",
  "description": "Produces a variety of ground units.",
  "type": "UnitFactory",
  
  "health": 100,
  "size": 2,

  "plans": [
    {
      "unit": "gueule-de-loup",
      "time": 200,
      "requirements": [
        "d-part/6",
        "alumin/2"
      ]
    },
    {
      "unit": "rockcress",
      "time": 200,
      "requirements": [
        "d-part/10",
        "t-part/4"
      ]
    }
  ],
  "configurable": true,

  "consumes": {
    "power": 4
  },

  "requirements": [
    "d-part/36",
    "m-part/36",
    "smart-compound/12"
  ],
  "category": "units",
  "research": {
    "parent": "civil-manufactory",
    "requirements": [
      "etherealium/20"
    ]
  }
}